db_backtest/BackTest.py
db_backtest/__init__.py
db_backtest/plot_utils.py
db_backtest/prepare.py
db_backtest/version.py
db_backtest-1.1.35.dist-info/METADATA
db_backtest-1.1.35.dist-info/WHEEL
db_backtest-1.1.35.dist-info/top_level.txt
db_backtest-1.1.35.dist-info/RECORD
